{
  "nightly": {
    "description": "Unstable",
    "hide": false,
    "last_updated": "2024-03-24T07:53:37.000Z",
    "last_updated_url": "https://github.com/hotio/stash/actions/runs/8407776554",
    "latest": false,
    "tags": [
      "nightly",
      "nightly-7086109d7879b64529578e3e16dcafbb8b57e842",
      "nightly-6c98b35"
    ]
  },
  "release": {
    "description": "Releases",
    "hide": false,
    "last_updated": "2024-03-13T03:49:40.000Z",
    "last_updated_url": "https://github.com/hotio/stash/actions/runs/8259180864",
    "latest": true,
    "tags": [
      "release",
      "release-0.25.1",
      "release-157ba77"
    ]
  }
}
